azure/cognitiveservices/language/luis/__init__.py
azure/cognitiveservices/language/luis/py.typed
azure/cognitiveservices/language/luis/version.py
azure/cognitiveservices/language/luis/authoring/__init__.py
azure/cognitiveservices/language/luis/authoring/_configuration.py
azure/cognitiveservices/language/luis/authoring/_luis_authoring_client.py
azure/cognitiveservices/language/luis/authoring/version.py
azure/cognitiveservices/language/luis/authoring/models/__init__.py
azure/cognitiveservices/language/luis/authoring/models/_luis_authoring_client_enums.py
azure/cognitiveservices/language/luis/authoring/models/_models.py
azure/cognitiveservices/language/luis/authoring/models/_models_py3.py
azure/cognitiveservices/language/luis/authoring/operations/__init__.py
azure/cognitiveservices/language/luis/authoring/operations/_apps_operations.py
azure/cognitiveservices/language/luis/authoring/operations/_azure_accounts_operations.py
azure/cognitiveservices/language/luis/authoring/operations/_examples_operations.py
azure/cognitiveservices/language/luis/authoring/operations/_features_operations.py
azure/cognitiveservices/language/luis/authoring/operations/_model_operations.py
azure/cognitiveservices/language/luis/authoring/operations/_pattern_operations.py
azure/cognitiveservices/language/luis/authoring/operations/_settings_operations.py
azure/cognitiveservices/language/luis/authoring/operations/_train_operations.py
azure/cognitiveservices/language/luis/authoring/operations/_versions_operations.py
azure/cognitiveservices/language/luis/runtime/__init__.py
azure/cognitiveservices/language/luis/runtime/_configuration.py
azure/cognitiveservices/language/luis/runtime/_luis_runtime_client.py
azure/cognitiveservices/language/luis/runtime/version.py
azure/cognitiveservices/language/luis/runtime/models/__init__.py
azure/cognitiveservices/language/luis/runtime/models/_models.py
azure/cognitiveservices/language/luis/runtime/models/_models_py3.py
azure_cognitiveservices_language_luis-0.7.1.dist-info/LICENSE
azure_cognitiveservices_language_luis-0.7.1.dist-info/METADATA
azure_cognitiveservices_language_luis-0.7.1.dist-info/WHEEL
azure_cognitiveservices_language_luis-0.7.1.dist-info/top_level.txt
azure_cognitiveservices_language_luis-0.7.1.dist-info/RECORD
